AUTHORS
COPYING
ChangeLog
INSTALL
LICENSE
NEWS
README
amazon_deploy_credentials.py
amazon_download.py
amazon_instance_extract.py
amazon_location_list.py
amazon_ls.py
amazon_nfs_config.py
amazon_openmpi_config.py
amazon_reservation_delete.py
amazon_reservation_list.py
amazon_reservation_pickup.py
amazon_reservation_run.py
amazon_reservations_delete.py
amazon_rm.py
amazon_rm_study.py
amazon_s3_clean.py
amazon_s3_list.py
amazon_send2cloud.py
amazon_solver_run.py
amazon_solver_run2.py
amazon_sqs_clean.py
amazon_upload_resume.py
amazon_upload_start.py
balloon_deploy.py
balloon_ssh.py
ez_setup.py
rackspace_clean.py
rackspace_fetch4queue.py
rackspace_run_server.py
rackspace_send2cloud.py
rackspace_servers-info.py
setup.py
balloon/__init__.py
balloon.egg-info/PKG-INFO
balloon.egg-info/SOURCES.txt
balloon.egg-info/dependency_links.txt
balloon.egg-info/requires.txt
balloon.egg-info/top_level.txt
balloon.egg-info/zip-safe
balloon/amazon/__init__.py
balloon/amazon/s3.py
balloon/amazon/ec2/__init__.py
balloon/amazon/ec2/common.py
balloon/amazon/ec2/run.py
balloon/amazon/ec2/use.py
balloon/common/__init__.py
balloon/common/ssh.py
balloon/rackspace/__init__.py