Metadata-Version: 1.0
Name: balloon
Version: 0.12-alfa
Summary: Set of cloud computing automation utilities
Home-page: http://sourceforge.net/p/cloud-foam
Author: Alexey Petrov
Author-email: alexey.petrov.nnov@gmail.com
License: Apache License, Version 2.0
Platform: linux
Classifier: Development Status :: 3 - Alpha
Classifier: Environment :: Console
Classifier: Intended Audience :: Science/Research
Classifier: License :: OSI Approved :: Apache Software License
Classifier: Operating System :: POSIX
Classifier: Programming Language :: Python
Classifier: Topic :: Scientific/Engineering
Classifier: Topic :: Utilities
